js.cookieconsent-3.1.0-py2.7-nspkg.pth
js/cookieconsent/__init__.py
js/cookieconsent/test_cookieconsent.rst
js/cookieconsent/resources/cookieconsent.js
js/cookieconsent/resources/cookieconsent.min.css
js/cookieconsent/resources/cookieconsent.min.js
js.cookieconsent-3.1.0.dist-info/DESCRIPTION.rst
js.cookieconsent-3.1.0.dist-info/METADATA
js.cookieconsent-3.1.0.dist-info/RECORD
js.cookieconsent-3.1.0.dist-info/WHEEL
js.cookieconsent-3.1.0.dist-info/entry_points.txt
js.cookieconsent-3.1.0.dist-info/metadata.json
js.cookieconsent-3.1.0.dist-info/namespace_packages.txt
js.cookieconsent-3.1.0.dist-info/top_level.txt
